Metadata-Version: 2.1
Name: PluginKernel
Version: 0.0.3
Summary: Plug-in Bandwidth Selection for Kernel Density Estimation with Discrete Data
Home-page: 
Author: Mehyar Mlaweh
Author-email: mehyarmlaweh0@gmail.com
License: MIT
Keywords: Kernel
Classifier: Development Status :: 5 - Production/Stable
Classifier: Intended Audience :: Science/Research
Classifier: Operating System :: Microsoft :: Windows :: Windows 10
Classifier: License :: OSI Approved :: MIT License
Classifier: Programming Language :: Python :: 3
License-File: LICENCE.txt
